dash_elasticsearch_autosuggest/ESAutosuggest.py
dash_elasticsearch_autosuggest/__init__.py
dash_elasticsearch_autosuggest/_imports_.py
dash_elasticsearch_autosuggest/dash_elasticsearch_autosuggest.dev.js
dash_elasticsearch_autosuggest/dash_elasticsearch_autosuggest.min.js
dash_elasticsearch_autosuggest/metadata.json
dash_elasticsearch_autosuggest/package.json
dash_elasticsearch_autosuggest-0.0.1.dist-info/LICENSE
dash_elasticsearch_autosuggest-0.0.1.dist-info/METADATA
dash_elasticsearch_autosuggest-0.0.1.dist-info/WHEEL
dash_elasticsearch_autosuggest-0.0.1.dist-info/top_level.txt
dash_elasticsearch_autosuggest-0.0.1.dist-info/RECORD
