Metadata-Version: 2.1
Name: dash-elasticsearch-autosuggest
Version: 0.0.1
Summary: React Autosuggest (WAI-ARIA compliant autosuggest component built in React) for Plotly Dash. Uses Elasticsearch to provide suggestions.
Home-page: UNKNOWN
Author: John Dagdelen jdagdelen@berkeley.edu
Author-email: UNKNOWN
License: MIT
Platform: UNKNOWN
